<?xml version="1.0" encoding="UTF-8" standalone="yes"?>
<npc xmlns:xsi="http://www.w3.org/2001/XMLSchema-instance" type="Monster" id="20139" xsi:schemaLocation="npc ../../npc.xsd" xsi:noNamespaceSchemaLocation="npc">
    <info aggressive="false" targetable="true" attackable="false">
        <name display="true" send="false">Giant Bee</name>
        <level>16</level>
        <sex>MALE</sex>
        <stats>
            <hp regen="2.5" max="264.34345"/>
            <mp regen="1.2" max="157.6"/>
            <attack critical="4" evasion="0" range="40">
                <physical speed="253.0" damage="32.16396"/>
                <magical speed="333.0" damage="21.96382"/>
            </attack>
            <defense>
                <physical value="76.08628"/>
                <magical value="50.6591"/>
            </defense>
            <move walk="90.0" run="90.0"/>
            <base wit="20" dex="30" men="20" con="43" str="40" int="21"/>
        </stats>
        <experience>471</experience>
        <sp>19</sp>
        <collision heigth="24.5" radius="8.0"/>
    </info>
</npc>
