<?xml version="1.0" encoding="UTF-8"?>
<npc type="Monster" id="21005" xsi:schemaLocation="npc ../../npc.xsd"
    xsi:noNamespaceSchemaLocation="npc" xmlns:xsi="http://www.w3.org/2001/XMLSchema-instance">
    <info aggressive="true" targetable="true" attackable="false">
        <name display="true" send="false">Grave Predator</name>
        <level>59</level>
        <sex>MALE</sex>
        <stats>
            <hp regen="6.5" max="1880.92519"/>
            <mp regen="2.4" max="1007.0"/>
            <attack critical="4" evasion="0" range="40">
                <physical speed="253.0" damage="461.94387"/>
                <magical speed="333.0" damage="315.44778"/>
            </attack>
            <defense>
                <physical value="242.81593"/>
                <magical value="161.66959"/>
            </defense>
            <move walk="25.0" run="174.0"/>
            <base wit="20" dex="30" men="20" con="43" str="40" int="21"/>
        </stats>
        <experience>6878</experience>
        <sp>588</sp>
        <collision heigth="35.0" radius="35.0"/>
    </info>
    <droplist>
        <item chance="700000" max="1876" min="920" id="57"/>
        <item chance="932" max="1" min="1" id="947"/>
        <item chance="114760" max="1" min="1" id="1868"/>
        <item chance="22952" max="1" min="1" id="1873"/>
        <item chance="11476" max="1" min="1" id="1876"/>
        <item chance="233106" max="1" min="1" id="1880"/>
        <item chance="16394" max="1" min="1" id="1895"/>
        <item chance="956" max="1" min="1" id="4042"/>
        <item chance="144427" max="1" min="1" id="4050"/>
        <item chance="657" max="1" min="1" id="4104"/>
        <item chance="647" max="1" min="1" id="4107"/>
        <item chance="647" max="1" min="1" id="4108"/>
        <item chance="621" max="1" min="1" id="4129"/>
        <item chance="714" max="1" min="1" id="4167"/>
        <item chance="44" max="1" min="1" id="4197"/>
        <item chance="956" max="1" min="1" id="8728"/>
        <item chance="239" max="1" min="1" id="8738"/>
        <item chance="24" max="1" min="1" id="8748"/>
        <item chance="5" max="1" min="1" id="8758"/>
        <item chance="66" max="1" min="1" id="11889"/>
        <item chance="66" max="1" min="1" id="11900"/>
        <item chance="66" max="1" min="1" id="11916"/>
    </droplist>
</npc>
