<?xml version="1.0" encoding="UTF-8"?>
<npc
    controller="com.l2jserver.model.world.npc.controller.MonsterController"
    id="21320" xsi:schemaLocation="npc ../../npc.xsd"
    xsi:noNamespaceSchemaLocation="npc" xmlns:xsi="http://www.w3.org/2001/XMLSchema-instance">
    <info aggressive="false" targetable="true" attackable="true">
        <name display="true" send="false">Hot Springs Yeti</name>
        <level>75</level>
        <race>GIANT</race>
        <sex>MALE</sex>
        <stats>
            <hp regen="8.5" max="2676.65854"/>
            <mp regen="3.0" max="1507.8"/>
            <attack critical="4" evasion="0" range="40">
                <physical speed="253.0" damage="794.70901"/>
                <magical speed="333.0" damage="542.68324"/>
            </attack>
            <defense>
                <physical value="319.24623"/>
                <magical value="212.55774"/>
            </defense>
            <move walk="16.0" run="170.0"/>
            <base wit="20" dex="30" men="20" con="43" str="40" int="21"/>
        </stats>
        <experience>22728</experience>
        <sp>2398</sp>
        <collision heigth="32.0" radius="18.0"/>
    </info>
    <droplist>
        <item chance="700000" category="DROP" max="6465" min="3168" id="57"/>
        <item chance="158111" category="UNK_2" max="3" min="1" id="1867"/>
        <item chance="105408" category="UNK_2" max="3" min="1" id="1872"/>
        <item chance="52704" category="UNK_2" max="1" min="1" id="1882"/>
        <item chance="225378" category="SPOIL" max="1" min="1" id="1894"/>
        <item chance="8322" category="UNK_2" max="1" min="1" id="1894"/>
        <item chance="105" category="UNK_2" max="1" min="1" id="3036"/>
        <item chance="108483" category="SPOIL" max="1" min="1" id="4042"/>
        <item chance="3953" category="UNK_2" max="1" min="1" id="4042"/>
        <item chance="107055" category="SPOIL" max="1" min="1" id="5503"/>
        <item chance="4035" category="UNK_1" max="1" min="1" id="5536"/>
        <item chance="2196" category="UNK_200" max="1" min="1" id="8731"/>
        <item chance="549" category="UNK_200" max="1" min="1" id="8741"/>
        <item chance="55" category="UNK_200" max="1" min="1" id="8751"/>
        <item chance="11" category="UNK_200" max="1" min="1" id="8761"/>
        <item chance="326" category="UNK_1" max="1" min="1" id="11951"/>
    </droplist>
    <skills>
        <skill level="8" id="4072"/>
        <skill level="8" id="4073"/>
        <skill level="1" id="4085"/>
        <skill level="1" id="4086"/>
        <skill level="1" id="4092"/>
        <skill level="10" id="4408"/>
        <skill level="1" id="4409"/>
        <skill level="11" id="4410"/>
        <skill level="11" id="4411"/>
        <skill level="11" id="4412"/>
        <skill level="11" id="4413"/>
        <skill level="2" id="4414"/>
        <skill level="3" id="4415"/>
        <skill level="11" id="4416"/>
        <skill level="2" id="4444"/>
        <skill level="1" id="4555"/>
        <skill level="4" id="4789"/>
    </skills>
</npc>
