<?xml version="1.0" encoding="UTF-8"?>
<npc
    controller="com.l2jserver.model.world.npc.controller.NotImplementedNPCController"
    id="22194" xsi:schemaLocation="npc ../../npc.xsd"
    xsi:noNamespaceSchemaLocation="npc" xmlns:xsi="http://www.w3.org/2001/XMLSchema-instance">
    <info aggressive="true" targetable="true" attackable="true">
        <name display="true" send="false">Penance Guard</name>
        <level>78</level>
        <sex>MALE</sex>
        <stats>
            <hp regen="8.721" max="2975.2369188"/>
            <mp regen="3.0804" max="1742.976"/>
            <attack critical="4" evasion="0" range="40">
                <physical speed="253.0" damage="938.20801"/>
                <magical speed="333.0" damage="656.66638"/>
            </attack>
            <defense>
                <physical value="354.81835"/>
                <magical value="259.64067"/>
            </defense>
            <move walk="33.0" run="120.0"/>
            <base wit="20" dex="30" men="20" con="43" str="40" int="21"/>
        </stats>
        <experience>3681</experience>
        <sp>397</sp>
        <item lefthand="0" righthand="8217"/>
        <collision heigth="22.0" radius="40.0"/>
    </info>
</npc>
