<?xml version="1.0" encoding="UTF-8"?>
<npc
    controller="com.l2jserver.model.world.npc.controller.MonsterController"
    id="22375" xsi:schemaLocation="npc ../../npc.xsd"
    xsi:noNamespaceSchemaLocation="npc" xmlns:xsi="http://www.w3.org/2001/XMLSchema-instance">
    <info aggressive="true" targetable="true" attackable="true">
        <name display="true" send="false">Cosmic Priest</name>
        <level>83</level>
        <race>DEMON</race>
        <sex>FEMALE</sex>
        <stats>
            <hp regen="190.745373183435" max="112316.37469612"/>
            <mp regen="3.0" max="1777.4"/>
            <attack critical="1" evasion="0" range="40">
                <physical speed="253.0" damage="9203.55602"/>
                <magical speed="333.0" damage="6357.91516"/>
            </attack>
            <defense>
                <physical value="585.59197"/>
                <magical value="642.76618"/>
            </defense>
            <move walk="46.0" run="165.0"/>
            <base wit="20" dex="30" men="20" con="43" str="40" int="21"/>
        </stats>
        <experience>533950</experience>
        <sp>56299</sp>
        <item lefthand="0" righthand="99"/>
        <collision heigth="28.0" radius="5.5"/>
    </info>
    <droplist>
        <item chance="700000" category="DROP" max="89941" min="44908" id="57"/>
        <item chance="655700" category="UNK_100" max="9" min="3" id="9599"/>
        <item chance="12947" category="UNK_1" max="1" min="1" id="8349"/>
        <item chance="12950" category="UNK_1" max="1" min="1" id="5533"/>
        <item chance="12937" category="UNK_1" max="1" min="1" id="5544"/>
        <item chance="12950" category="UNK_1" max="1" min="1" id="8342"/>
        <item chance="46" category="UNK_1" max="1" min="1" id="164"/>
        <item chance="46" category="UNK_1" max="1" min="1" id="213"/>
        <item chance="46" category="UNK_1" max="1" min="1" id="7895"/>
        <item chance="46" category="UNK_1" max="1" min="1" id="7902"/>
        <item chance="34970" category="UNK_2" max="360" min="120" id="1868"/>
        <item chance="69940" category="UNK_2" max="36" min="12" id="1873"/>
        <item chance="31085" category="UNK_2" max="12" min="4" id="1889"/>
        <item chance="139881" category="UNK_2" max="1" min="1" id="4044"/>
        <item chance="59949" category="UNK_2" max="9" min="3" id="5549"/>
        <item chance="33571" category="UNK_200" max="1" min="1" id="9551"/>
        <item chance="4196" category="UNK_2" max="1" min="1" id="6901"/>
        <item chance="5663" category="UNK_2" max="1" min="1" id="6851"/>
        <item chance="1608" category="UNK_2" max="1" min="1" id="6873"/>
        <item chance="186089" category="SPOIL" max="1" min="1" id="8715"/>
        <item chance="851874" category="SPOIL" max="5" min="1" id="4044"/>
        <item chance="30667" category="SPOIL" max="1" min="1" id="960"/>
    </droplist>
    <skills>
        <skill level="1" id="4408"/>
        <skill level="1" id="4409"/>
        <skill level="11" id="4410"/>
        <skill level="11" id="4411"/>
        <skill level="11" id="4412"/>
        <skill level="11" id="4413"/>
        <skill level="3" id="4414"/>
        <skill level="5" id="4415"/>
        <skill level="9" id="4416"/>
        <skill level="3" id="5328"/>
        <skill level="3" id="5372"/>
        <skill level="1" id="5467"/>
        <skill level="9" id="5529"/>
    </skills>
</npc>
