<?xml version="1.0" encoding="UTF-8"?>
<npc
    controller="com.l2jserver.model.world.npc.controller.NotImplementedNPCController"
    id="22453" xsi:schemaLocation="npc ../../npc.xsd"
    xsi:noNamespaceSchemaLocation="npc" xmlns:xsi="http://www.w3.org/2001/XMLSchema-instance">
    <info aggressive="false" targetable="true" attackable="true">
        <name display="true" send="false">White Skull Kanabion</name>
        <title send="false">Doppler</title>
        <level>25</level>
        <sex>MALE</sex>
        <stats>
            <hp regen="3.5" max="460.96247"/>
            <mp regen="1.5" max="259.2"/>
            <attack critical="4" evasion="0" range="80">
                <physical speed="253.0" damage="64.83203"/>
                <magical speed="333.0" damage="44.27187"/>
            </attack>
            <defense>
                <physical value="101.83533"/>
                <magical value="74.51868"/>
            </defense>
            <move walk="40.0" run="160.0"/>
            <base wit="20" dex="30" men="20" con="43" str="40" int="21"/>
        </stats>
        <experience>1136</experience>
        <sp>56</sp>
        <item lefthand="0" righthand="5285"/>
        <collision heigth="30.5" radius="12.0"/>
    </info>
    <droplist>
        <item chance="11100" max="1" min="1" id="956"/>
    </droplist>
</npc>
