<?xml version="1.0" encoding="UTF-8" standalone="yes"?>
<npc xmlns:xsi="http://www.w3.org/2001/XMLSchema-instance" type="Monster" id="22639" xsi:schemaLocation="npc ../../npc.xsd" xsi:noNamespaceSchemaLocation="npc">
    <info aggressive="false" targetable="true" attackable="false">
        <name display="true" send="false">Assassin Beetle</name>
        <level>78</level>
        <sex>MALE</sex>
        <stats>
            <hp regen="8.5" max="2974.35686398316"/>
            <mp regen="3.0" max="1607.4"/>
            <attack critical="4" evasion="0" range="40">
                <physical speed="253.0" damage="890.50086"/>
                <magical speed="333.0" damage="608.09666"/>
            </attack>
            <defense>
                <physical value="332.70061"/>
                <magical value="243.45587"/>
            </defense>
            <move walk="45.0" run="145.0"/>
            <base wit="20" dex="30" men="20" con="43" str="40" int="21"/>
        </stats>
        <experience>37745</experience>
        <sp>3937</sp>
        <collision heigth="54.5" radius="19.0"/>
    </info>
    <droplist>
        <item chance="700000" max="4200" min="2600" id="57"/>
        <item chance="9000" max="1" min="1" id="6710"/>
        <item chance="9000" max="1" min="1" id="6705"/>
        <item chance="30" max="1" min="1" id="13885"/>
        <item chance="30" max="1" min="1" id="6678"/>
        <item chance="20" max="1" min="1" id="6679"/>
        <item chance="20" max="1" min="1" id="6683"/>
        <item chance="20" max="1" min="1" id="6687"/>
        <item chance="210000" max="1" min="1" id="1895"/>
        <item chance="20000" max="1" min="1" id="4043"/>
        <item chance="20000" max="1" min="1" id="4040"/>
        <item chance="10000" max="1" min="1" id="4042"/>
        <item chance="300" max="1" min="1" id="9548"/>
        <item chance="40000" max="1" min="1" id="7579"/>
        <item chance="40000" max="1" min="1" id="6695"/>
        <item chance="3000" max="1" min="1" id="5282"/>
    </droplist>
</npc>
