<?xml version="1.0" encoding="UTF-8"?>
<npc
    controller="com.l2jserver.model.world.npc.controller.MonsterController"
    id="25058" xsi:schemaLocation="npc ../../npc.xsd"
    xsi:noNamespaceSchemaLocation="npc" xmlns:xsi="http://www.w3.org/2001/XMLSchema-instance">
    <info aggressive="false" targetable="true" attackable="true">
        <name display="true" send="false">Biconne's Shooter</name>
        <title send="false">Raid Fighter</title>
        <level>44</level>
        <race>UNDEAD</race>
        <sex>MALE</sex>
        <stats>
            <hp regen="41.3470424277186" max="12313.3984354286"/>
            <mp regen="2.1" max="584.0"/>
            <attack critical="8" evasion="0" range="1100">
                <physical speed="253.0" damage="624.12426"/>
                <magical speed="333.0" damage="130.5309"/>
            </attack>
            <defense>
                <physical value="260.15328"/>
                <magical value="253.82"/>
            </defense>
            <move walk="40.0" run="170.0"/>
            <base wit="20" dex="30" men="20" con="43" str="40" int="21"/>
        </stats>
        <experience>0</experience>
        <sp>0</sp>
        <item lefthand="0" righthand="279"/>
        <collision heigth="27.0" radius="11.0"/>
    </info>
    <droplist>
        <item chance="559200" category="UNK_2" max="60" min="20" id="1342"/>
    </droplist>
    <skills>
        <skill level="1" id="4045"/>
        <skill level="1" id="4408"/>
        <skill level="1" id="4409"/>
        <skill level="11" id="4410"/>
        <skill level="11" id="4411"/>
        <skill level="11" id="4412"/>
        <skill level="11" id="4413"/>
        <skill level="3" id="4414"/>
        <skill level="9" id="4415"/>
        <skill level="1" id="4416"/>
        <skill level="5" id="4757"/>
    </skills>
</npc>
